matOpsPy/__init__.py
matOpsPy/matOpsPy.cpython-311-x86_64-linux-gnu.so
matOpsPy/matOpsPy.pyi
matOpsPy-0.3.0.dist-info/METADATA
matOpsPy-0.3.0.dist-info/WHEEL
matOpsPy-0.3.0.dist-info/top_level.txt
matOpsPy-0.3.0.dist-info/RECORD
